<SceneText>
  <Speakers>
    <Section>Speaker</Section>
    <Entry>
      <PointerOffset/>
      <JapaneseText>IO)</JapaneseText>
      <EnglishText/>
      <Notes/>
      <Id>1</Id>
      <Status>To Do</Status>
    </Entry>
    <Entry>
      <PointerOffset/>
      <JapaneseText>シグルドの兵士</JapaneseText>
      <EnglishText/>
      <Notes/>
      <Id>2</Id>
      <Status>To Do</Status>
    </Entry>
    <Entry>
      <PointerOffset/>
      <JapaneseText>Variable</JapaneseText>
      <EnglishText/>
      <Notes/>
      <Id>3</Id>
      <Status>To Do</Status>
    </Entry>
  </Speakers>
  <Strings>
    <Section>Story</Section>
    <Entry>
      <PointerOffset>258884</PointerOffset>
      <VoiceId>VSM_140_050_001</VoiceId>
      <JapaneseText>待て！</JapaneseText>
      <EnglishText/>
      <Notes/>
      <SpeakerId>1</SpeakerId>
      <Id>1</Id>
      <BubbleId>1</BubbleId>
      <SubId>1</SubId>
      <Status>To Do</Status>
    </Entry>
    <Entry>
      <PointerOffset>258884</PointerOffset>
      <JapaneseText></JapaneseText>
      <EnglishText/>
      <Notes/>
      <SpeakerId>1</SpeakerId>
      <Id>1</Id>
      <BubbleId>1</BubbleId>
      <SubId>2</SubId>
      <Status>To Do</Status>
    </Entry>
    <Entry>
      <PointerOffset>258884</PointerOffset>
      <JapaneseText></JapaneseText>
      <EnglishText/>
      <Notes/>
      <SpeakerId>1</SpeakerId>
      <Id>1</Id>
      <BubbleId>1</BubbleId>
      <SubId>3</SubId>
      <Status>To Do</Status>
    </Entry>
    <Entry>
      <PointerOffset>259024</PointerOffset>
      <VoiceId>VSM_140_050_002</VoiceId>
      <JapaneseText>くそっ……</JapaneseText>
      <EnglishText/>
      <Notes/>
      <SpeakerId>2</SpeakerId>
      <Id>2</Id>
      <BubbleId>1</BubbleId>
      <SubId>1</SubId>
      <Status>To Do</Status>
    </Entry>
    <Entry>
      <PointerOffset>259024</PointerOffset>
      <JapaneseText></JapaneseText>
      <EnglishText/>
      <Notes/>
      <SpeakerId>2</SpeakerId>
      <Id>2</Id>
      <BubbleId>1</BubbleId>
      <SubId>2</SubId>
      <Status>To Do</Status>
    </Entry>
    <Entry>
      <PointerOffset>259024</PointerOffset>
      <JapaneseText></JapaneseText>
      <EnglishText/>
      <Notes/>
      <SpeakerId>2</SpeakerId>
      <Id>2</Id>
      <BubbleId>1</BubbleId>
      <SubId>3</SubId>
      <Status>To Do</Status>
    </Entry>
  </Strings>
</SceneText>
