<SceneText>
  <Speakers>
    <Section>Speaker</Section>
    <Entry>
      <PointerOffset/>
      <JapaneseText>&lt;Claus&gt;</JapaneseText>
      <EnglishText/>
      <Notes/>
      <Id>1</Id>
      <Status>To Do</Status>
    </Entry>
    <Entry>
      <PointerOffset/>
      <JapaneseText>&lt;Dio&gt;</JapaneseText>
      <EnglishText/>
      <Notes/>
      <Id>2</Id>
      <Status>To Do</Status>
    </Entry>
    <Entry>
      <PointerOffset/>
      <JapaneseText>エトス</JapaneseText>
      <EnglishText/>
      <Notes/>
      <Id>3</Id>
      <Status>To Do</Status>
    </Entry>
    <Entry>
      <PointerOffset/>
      <JapaneseText>&lt;Mel&gt;</JapaneseText>
      <EnglishText/>
      <Notes/>
      <Id>4</Id>
      <Status>To Do</Status>
    </Entry>
    <Entry>
      <PointerOffset/>
      <JapaneseText>Variable</JapaneseText>
      <EnglishText/>
      <Notes/>
      <Id>5</Id>
      <Status>To Do</Status>
    </Entry>
  </Speakers>
  <Strings>
    <Section>Story</Section>
    <Entry>
      <PointerOffset>262736</PointerOffset>
      <JapaneseText>ちょっと待っていてくれ</JapaneseText>
      <EnglishText/>
      <Notes/>
      <SpeakerId>1</SpeakerId>
      <Id>1</Id>
      <BubbleId>1</BubbleId>
      <Status>To Do</Status>
    </Entry>
    <Entry>
      <PointerOffset>263220</PointerOffset>
      <JapaneseText>……&lt;Claus&gt;さん、
きっとこっそり、
父ちゃんの手紙見たんだぜ</JapaneseText>
      <EnglishText/>
      <Notes/>
      <SpeakerId>2</SpeakerId>
      <Id>2</Id>
      <BubbleId>1</BubbleId>
      <Status>To Do</Status>
    </Entry>
    <Entry>
      <PointerOffset>263632</PointerOffset>
      <JapaneseText>手紙ってミラルドさんに
渡されたあれのこと？</JapaneseText>
      <EnglishText/>
      <Notes/>
      <SpeakerId>3</SpeakerId>
      <Id>3</Id>
      <BubbleId>1</BubbleId>
      <Status>To Do</Status>
    </Entry>
    <Entry>
      <PointerOffset>263940</PointerOffset>
      <JapaneseText>ここの井戸に&lt;Claus&gt;さんの
父ちゃんが何か隠したって
書いてあったもん</JapaneseText>
      <EnglishText/>
      <Notes/>
      <SpeakerId>2</SpeakerId>
      <Id>4</Id>
      <BubbleId>1</BubbleId>
      <Status>To Do</Status>
    </Entry>
    <Entry>
      <PointerOffset>264136</PointerOffset>
      <JapaneseText>&lt;Dio&gt;、中身見たの……？</JapaneseText>
      <EnglishText/>
      <Notes/>
      <SpeakerId>4</SpeakerId>
      <Id>5</Id>
      <BubbleId>1</BubbleId>
      <Status>To Do</Status>
    </Entry>
    <Entry>
      <PointerOffset>264500</PointerOffset>
      <JapaneseText>え、あ、うん……
あれ？　まずかったか……？</JapaneseText>
      <EnglishText/>
      <Notes/>
      <SpeakerId>2</SpeakerId>
      <Id>6</Id>
      <BubbleId>1</BubbleId>
      <Status>To Do</Status>
    </Entry>
    <Entry>
      <PointerOffset>264912</PointerOffset>
      <JapaneseText>……きみ、ねぇ……</JapaneseText>
      <EnglishText/>
      <Notes/>
      <SpeakerId>3</SpeakerId>
      <Id>7</Id>
      <BubbleId>1</BubbleId>
      <Status>To Do</Status>
    </Entry>
    <Entry>
      <PointerOffset>265336</PointerOffset>
      <JapaneseText>でも、結局、&lt;Claus&gt;さん、
手紙読んだんだね……</JapaneseText>
      <EnglishText/>
      <Notes/>
      <SpeakerId>4</SpeakerId>
      <Id>8</Id>
      <BubbleId>1</BubbleId>
      <Status>To Do</Status>
    </Entry>
    <Entry>
      <PointerOffset>265696</PointerOffset>
      <JapaneseText>……あった……</JapaneseText>
      <EnglishText/>
      <Notes/>
      <SpeakerId>1</SpeakerId>
      <Id>9</Id>
      <BubbleId>1</BubbleId>
      <Status>To Do</Status>
    </Entry>
    <Entry>
      <PointerOffset>266972</PointerOffset>
      <JapaneseText>よし、いいぞ</JapaneseText>
      <EnglishText/>
      <Notes/>
      <SpeakerId>1</SpeakerId>
      <Id>10</Id>
      <BubbleId>1</BubbleId>
      <Status>To Do</Status>
    </Entry>
    <Entry>
      <PointerOffset>267804</PointerOffset>
      <JapaneseText>何だったんだ？</JapaneseText>
      <EnglishText/>
      <Notes/>
      <SpeakerId>2</SpeakerId>
      <Id>11</Id>
      <BubbleId>1</BubbleId>
      <Status>To Do</Status>
    </Entry>
    <Entry>
      <PointerOffset>268072</PointerOffset>
      <JapaneseText>何ってこともない。
武器がひとつ見つかっただけだ</JapaneseText>
      <EnglishText/>
      <Notes/>
      <SpeakerId>1</SpeakerId>
      <Id>12</Id>
      <BubbleId>1</BubbleId>
      <Status>To Do</Status>
    </Entry>
    <Entry>
      <PointerOffset>268212</PointerOffset>
      <JapaneseText>父ちゃんのプレゼントって
武器だったんだな</JapaneseText>
      <EnglishText/>
      <Notes/>
      <SpeakerId>2</SpeakerId>
      <Id>13</Id>
      <BubbleId>1</BubbleId>
      <Status>To Do</Status>
    </Entry>
    <Entry>
      <PointerOffset>268652</PointerOffset>
      <JapaneseText>しょうがないな。
きみも父からの手紙を読んだのか</JapaneseText>
      <EnglishText/>
      <Notes/>
      <SpeakerId>1</SpeakerId>
      <Id>14</Id>
      <BubbleId>1</BubbleId>
      <Status>To Do</Status>
    </Entry>
    <Entry>
      <PointerOffset>268848</PointerOffset>
      <JapaneseText>ご、ごめんなさい</JapaneseText>
      <EnglishText/>
      <Notes/>
      <SpeakerId>2</SpeakerId>
      <Id>15</Id>
      <BubbleId>1</BubbleId>
      <Status>To Do</Status>
    </Entry>
    <Entry>
      <PointerOffset>269044</PointerOffset>
      <JapaneseText>いや、いいんだ……
ふっ……まったく驚きだな</JapaneseText>
      <EnglishText/>
      <Notes/>
      <SpeakerId>1</SpeakerId>
      <Id>16</Id>
      <BubbleId>1</BubbleId>
      <Status>To Do</Status>
    </Entry>
    <Entry>
      <PointerOffset>269044</PointerOffset>
      <JapaneseText>謝罪の言葉で埋めつくされてる
手紙なんて</JapaneseText>
      <EnglishText/>
      <Notes/>
      <SpeakerId>1</SpeakerId>
      <Id>16</Id>
      <BubbleId>2</BubbleId>
      <Status>To Do</Status>
    </Entry>
    <Entry>
      <PointerOffset>269304</PointerOffset>
      <JapaneseText>そう……
だったんですか？</JapaneseText>
      <EnglishText/>
      <Notes/>
      <SpeakerId>4</SpeakerId>
      <Id>17</Id>
      <BubbleId>1</BubbleId>
      <Status>To Do</Status>
    </Entry>
    <Entry>
      <PointerOffset>269668</PointerOffset>
      <JapaneseText>ああ……うちの父は
家庭を顧みず、研究に没頭した</JapaneseText>
      <EnglishText/>
      <Notes/>
      <SpeakerId>1</SpeakerId>
      <Id>18</Id>
      <BubbleId>1</BubbleId>
      <Status>To Do</Status>
    </Entry>
    <Entry>
      <PointerOffset>269668</PointerOffset>
      <JapaneseText>そうであったことを
ずっと後悔してたんだと</JapaneseText>
      <EnglishText/>
      <Notes/>
      <SpeakerId>1</SpeakerId>
      <Id>18</Id>
      <BubbleId>2</BubbleId>
      <Status>To Do</Status>
    </Entry>
    <Entry>
      <PointerOffset>269668</PointerOffset>
      <JapaneseText>もっと私と話をしとけばよかった、
母との時間も作っておけばよかった</JapaneseText>
      <EnglishText/>
      <Notes/>
      <SpeakerId>1</SpeakerId>
      <Id>18</Id>
      <BubbleId>3</BubbleId>
      <Status>To Do</Status>
    </Entry>
    <Entry>
      <PointerOffset>269668</PointerOffset>
      <JapaneseText>後悔することはたくさんあるが、
それでも研究をすることも
自分には大切だったんだとな</JapaneseText>
      <EnglishText/>
      <Notes/>
      <SpeakerId>1</SpeakerId>
      <Id>18</Id>
      <BubbleId>4</BubbleId>
      <Status>To Do</Status>
    </Entry>
    <Entry>
      <PointerOffset>269668</PointerOffset>
      <JapaneseText>私にも……今なら、ほんの少し
その気持ちがわかる</JapaneseText>
      <EnglishText/>
      <Notes/>
      <SpeakerId>1</SpeakerId>
      <Id>18</Id>
      <BubbleId>5</BubbleId>
      <Status>To Do</Status>
    </Entry>
    <Entry>
      <PointerOffset>271372</PointerOffset>
      <JapaneseText>そうなのか？</JapaneseText>
      <EnglishText/>
      <Notes/>
      <SpeakerId>2</SpeakerId>
      <Id>19</Id>
      <BubbleId>1</BubbleId>
      <Status>To Do</Status>
    </Entry>
    <Entry>
      <PointerOffset>271804</PointerOffset>
      <JapaneseText>時々、研究に没頭して、
周囲が見えなくなることも
少なくないからな</JapaneseText>
      <EnglishText/>
      <Notes/>
      <SpeakerId>1</SpeakerId>
      <Id>20</Id>
      <BubbleId>1</BubbleId>
      <Status>To Do</Status>
    </Entry>
    <Entry>
      <PointerOffset>271804</PointerOffset>
      <JapaneseText>私もいつか……
父のように後悔する時が
来るのだろうか……</JapaneseText>
      <EnglishText/>
      <Notes/>
      <SpeakerId>1</SpeakerId>
      <Id>20</Id>
      <BubbleId>2</BubbleId>
      <Status>To Do</Status>
    </Entry>
    <Entry>
      <PointerOffset>272064</PointerOffset>
      <JapaneseText>でもさ、最後にそうならねー
ように毎日、大切に過ごせ
って書いてあったろ</JapaneseText>
      <EnglishText/>
      <Notes/>
      <SpeakerId>2</SpeakerId>
      <Id>21</Id>
      <BubbleId>1</BubbleId>
      <Status>To Do</Status>
    </Entry>
    <Entry>
      <PointerOffset>272428</PointerOffset>
      <JapaneseText>ふっ、自分に
できなかったことを
簡単に言ってくれるな</JapaneseText>
      <EnglishText/>
      <Notes/>
      <SpeakerId>1</SpeakerId>
      <Id>22</Id>
      <BubbleId>1</BubbleId>
      <Status>To Do</Status>
    </Entry>
    <Entry>
      <PointerOffset>272428</PointerOffset>
      <JapaneseText>でも……肝に銘じるとするよ、
反面教師として……親父</JapaneseText>
      <EnglishText/>
      <Notes/>
      <SpeakerId>1</SpeakerId>
      <Id>22</Id>
      <BubbleId>2</BubbleId>
      <Status>To Do</Status>
    </Entry>
  </Strings>
</SceneText>
