<SceneText>
  <Speakers>
    <Section>Speaker</Section>
    <Entry>
      <PointerOffset/>
      <JapaneseText>&lt;Rondoline&gt;</JapaneseText>
      <EnglishText>&lt;Rondoline&gt;</EnglishText>
      <Notes/>
      <Id>1</Id>
      <Status>Done</Status>
    </Entry>
    <Entry>
      <PointerOffset/>
      <JapaneseText>&lt;Mel&gt;</JapaneseText>
      <EnglishText>&lt;Mel&gt;</EnglishText>
      <Notes/>
      <Id>2</Id>
      <Status>Done</Status>
    </Entry>
    <Entry>
      <PointerOffset/>
      <JapaneseText>エトス</JapaneseText>
      <EnglishText>Ethos</EnglishText>
      <Notes/>
      <Id>3</Id>
      <Status>Done</Status>
    </Entry>
    <Entry>
      <PointerOffset/>
      <JapaneseText>&lt;Dio&gt;</JapaneseText>
      <EnglishText>&lt;Dio&gt;</EnglishText>
      <Notes/>
      <Id>4</Id>
      <Status>Done</Status>
    </Entry>
    <Entry>
      <PointerOffset/>
      <JapaneseText>Variable</JapaneseText>
      <EnglishText>Variable</EnglishText>
      <Notes/>
      <Id>5</Id>
      <Status>Done</Status>
    </Entry>
  </Speakers>
  <Strings>
    <Section>Story</Section>
    <Entry>
      <PointerOffset>258412</PointerOffset>
      <JapaneseText>なに、この柱のキズ</JapaneseText>
      <EnglishText/>
      <Notes/>
      <SpeakerId>1</SpeakerId>
      <Id>1</Id>
      <BubbleId>1</BubbleId>
      <Status>To Do</Status>
    </Entry>
    <Entry>
      <PointerOffset>258412</PointerOffset>
      <JapaneseText>あ……&lt;Dio&gt;くんが
暴れた跡？
いや、&lt;Mel&gt;ちゃんか？</JapaneseText>
      <EnglishText/>
      <Notes/>
      <SpeakerId>1</SpeakerId>
      <Id>1</Id>
      <BubbleId>2</BubbleId>
      <Status>To Do</Status>
    </Entry>
    <Entry>
      <PointerOffset>258608</PointerOffset>
      <JapaneseText>ち、違いますよ。
それはふたりの背を
測った跡です</JapaneseText>
      <EnglishText/>
      <Notes/>
      <SpeakerId>2</SpeakerId>
      <Id>2</Id>
      <BubbleId>1</BubbleId>
      <Status>To Do</Status>
    </Entry>
    <Entry>
      <PointerOffset>258748</PointerOffset>
      <JapaneseText>あ……よく見たら、
数字が書いてある</JapaneseText>
      <EnglishText/>
      <Notes/>
      <SpeakerId>1</SpeakerId>
      <Id>3</Id>
      <BubbleId>1</BubbleId>
      <Status>To Do</Status>
    </Entry>
    <Entry>
      <PointerOffset>258888</PointerOffset>
      <JapaneseText>初めはわたしの方が
伸びるの早かったけど</JapaneseText>
      <EnglishText/>
      <Notes/>
      <SpeakerId>2</SpeakerId>
      <Id>4</Id>
      <BubbleId>1</BubbleId>
      <Status>To Do</Status>
    </Entry>
    <Entry>
      <PointerOffset>258888</PointerOffset>
      <JapaneseText>&lt;Dio&gt;はここ２、３年で
急に背が伸びたね</JapaneseText>
      <EnglishText/>
      <Notes/>
      <SpeakerId>2</SpeakerId>
      <Id>4</Id>
      <BubbleId>2</BubbleId>
      <Status>To Do</Status>
    </Entry>
    <Entry>
      <PointerOffset>259376</PointerOffset>
      <JapaneseText>寝る子は育つって
言うかラ</JapaneseText>
      <EnglishText/>
      <Notes/>
      <SpeakerId>3</SpeakerId>
      <Id>5</Id>
      <BubbleId>1</BubbleId>
      <Status>To Do</Status>
    </Entry>
    <Entry>
      <PointerOffset>259572</PointerOffset>
      <JapaneseText>『寝る子』？</JapaneseText>
      <EnglishText/>
      <Notes/>
      <SpeakerId>1</SpeakerId>
      <Id>6</Id>
      <BubbleId>1</BubbleId>
      <Status>To Do</Status>
    </Entry>
    <Entry>
      <PointerOffset>259816</PointerOffset>
      <JapaneseText>１日１２時間は平気で
寝てたもんね</JapaneseText>
      <EnglishText/>
      <Notes/>
      <SpeakerId>3</SpeakerId>
      <Id>7</Id>
      <BubbleId>1</BubbleId>
      <Status>To Do</Status>
    </Entry>
    <Entry>
      <PointerOffset>260060</PointerOffset>
      <JapaneseText>しょうがねだろ。
疲れてたんだから</JapaneseText>
      <EnglishText/>
      <Notes/>
      <SpeakerId>4</SpeakerId>
      <Id>8</Id>
      <BubbleId>1</BubbleId>
      <Status>To Do</Status>
    </Entry>
    <Entry>
      <PointerOffset>260200</PointerOffset>
      <JapaneseText>……森の中に遊びに出て、
うろうろしてたら、
そりゃ疲れるよ</JapaneseText>
      <EnglishText/>
      <Notes/>
      <SpeakerId>3</SpeakerId>
      <Id>9</Id>
      <BubbleId>1</BubbleId>
      <Status>To Do</Status>
    </Entry>
    <Entry>
      <PointerOffset>260340</PointerOffset>
      <JapaneseText>疲れてふらふらして、
足踏み外して
崖から落ちるしね</JapaneseText>
      <EnglishText/>
      <Notes/>
      <SpeakerId>2</SpeakerId>
      <Id>10</Id>
      <BubbleId>1</BubbleId>
      <Status>To Do</Status>
    </Entry>
    <Entry>
      <PointerOffset>260696</PointerOffset>
      <JapaneseText>あれは遊びじゃなくて、
調査だって</JapaneseText>
      <EnglishText/>
      <Notes/>
      <SpeakerId>4</SpeakerId>
      <Id>11</Id>
      <BubbleId>1</BubbleId>
      <Status>To Do</Status>
    </Entry>
    <Entry>
      <PointerOffset>260696</PointerOffset>
      <JapaneseText>&lt;Red&gt;エトスハウス&lt;White&gt;の周りに
危険な場所がねーか
魔物がいないかってさ</JapaneseText>
      <EnglishText/>
      <Notes/>
      <SpeakerId>4</SpeakerId>
      <Id>11</Id>
      <BubbleId>2</BubbleId>
      <Status>To Do</Status>
    </Entry>
    <Entry>
      <PointerOffset>260836</PointerOffset>
      <JapaneseText>嘘だぁ……</JapaneseText>
      <EnglishText/>
      <Notes/>
      <SpeakerId>2</SpeakerId>
      <Id>12</Id>
      <BubbleId>1</BubbleId>
      <Status>To Do</Status>
    </Entry>
    <Entry>
      <PointerOffset>261032</PointerOffset>
      <JapaneseText>そうだ……！</JapaneseText>
      <EnglishText/>
      <Notes/>
      <SpeakerId>4</SpeakerId>
      <Id>13</Id>
      <BubbleId>1</BubbleId>
      <Status>To Do</Status>
    </Entry>
    <Entry>
      <PointerOffset>261540</PointerOffset>
      <JapaneseText>どうしたの、&lt;Dio&gt;くん</JapaneseText>
      <EnglishText/>
      <Notes/>
      <SpeakerId>1</SpeakerId>
      <Id>14</Id>
      <BubbleId>1</BubbleId>
      <Status>To Do</Status>
    </Entry>
    <Entry>
      <PointerOffset>261680</PointerOffset>
      <JapaneseText>さぁ……</JapaneseText>
      <EnglishText/>
      <Notes/>
      <SpeakerId>2</SpeakerId>
      <Id>15</Id>
      <BubbleId>1</BubbleId>
      <Status>To Do</Status>
    </Entry>
    <Entry>
      <PointerOffset>261820</PointerOffset>
      <JapaneseText>&lt;Dio&gt;も&lt;Mel&gt;も……
まだまだ……もっともっと、
大きくなるんだね</JapaneseText>
      <EnglishText/>
      <Notes/>
      <SpeakerId>3</SpeakerId>
      <Id>16</Id>
      <BubbleId>1</BubbleId>
      <Status>To Do</Status>
    </Entry>
    <Entry>
      <PointerOffset>262072</PointerOffset>
      <JapaneseText>……エトちゃーん、
寂しいんでしょ</JapaneseText>
      <EnglishText/>
      <Notes/>
      <SpeakerId>1</SpeakerId>
      <Id>17</Id>
      <BubbleId>1</BubbleId>
      <Status>To Do</Status>
    </Entry>
    <Entry>
      <PointerOffset>262316</PointerOffset>
      <JapaneseText>え……ち、違うよ。
寂しいっていうか、
嬉しい、かな……</JapaneseText>
      <EnglishText/>
      <Notes/>
      <SpeakerId>3</SpeakerId>
      <Id>18</Id>
      <BubbleId>1</BubbleId>
      <Status>To Do</Status>
    </Entry>
    <Entry>
      <PointerOffset>262316</PointerOffset>
      <JapaneseText>ちっちゃい頃はいつも
ぼくに甘えてた&lt;Dio&gt;が</JapaneseText>
      <EnglishText/>
      <Notes/>
      <SpeakerId>3</SpeakerId>
      <Id>18</Id>
      <BubbleId>2</BubbleId>
      <Status>To Do</Status>
    </Entry>
    <Entry>
      <PointerOffset>262316</PointerOffset>
      <JapaneseText>あんなふうに、
口答えするのも……
なんか嬉しいんだ……</JapaneseText>
      <EnglishText/>
      <Notes/>
      <SpeakerId>3</SpeakerId>
      <Id>18</Id>
      <BubbleId>3</BubbleId>
      <Status>To Do</Status>
    </Entry>
    <Entry>
      <PointerOffset>262512</PointerOffset>
      <JapaneseText>&lt;Mel&gt;ちゃんも
あまえんぼさん
卒業しちゃったしね</JapaneseText>
      <EnglishText/>
      <Notes/>
      <SpeakerId>1</SpeakerId>
      <Id>19</Id>
      <BubbleId>1</BubbleId>
      <Status>To Do</Status>
    </Entry>
    <Entry>
      <PointerOffset>262812</PointerOffset>
      <JapaneseText>え？　わ、わたし、
あまえんぼさんじゃ
ないですよ？</JapaneseText>
      <EnglishText/>
      <Notes/>
      <SpeakerId>2</SpeakerId>
      <Id>20</Id>
      <BubbleId>1</BubbleId>
      <Status>To Do</Status>
    </Entry>
    <Entry>
      <PointerOffset>263388</PointerOffset>
      <JapaneseText>おまたせー</JapaneseText>
      <EnglishText/>
      <Notes/>
      <SpeakerId>4</SpeakerId>
      <Id>21</Id>
      <BubbleId>1</BubbleId>
      <Status>To Do</Status>
    </Entry>
    <Entry>
      <PointerOffset>263528</PointerOffset>
      <JapaneseText>何持ってきたの？</JapaneseText>
      <EnglishText/>
      <Notes/>
      <SpeakerId>2</SpeakerId>
      <Id>22</Id>
      <BubbleId>1</BubbleId>
      <Status>To Do</Status>
    </Entry>
    <Entry>
      <PointerOffset>263668</PointerOffset>
      <JapaneseText>デッキブラシだよ</JapaneseText>
      <EnglishText/>
      <Notes/>
      <SpeakerId>4</SpeakerId>
      <Id>23</Id>
      <BubbleId>1</BubbleId>
      <Status>To Do</Status>
    </Entry>
    <Entry>
      <PointerOffset>263668</PointerOffset>
      <JapaneseText>森の中に出かける時、
いつも武器に持ってただろ</JapaneseText>
      <EnglishText/>
      <Notes/>
      <SpeakerId>4</SpeakerId>
      <Id>23</Id>
      <BubbleId>2</BubbleId>
      <Status>To Do</Status>
    </Entry>
    <Entry>
      <PointerOffset>263668</PointerOffset>
      <JapaneseText>やっぱさ、しっくりと
手になじんでる武器、
使いたいよなー</JapaneseText>
      <EnglishText/>
      <Notes/>
      <SpeakerId>4</SpeakerId>
      <Id>23</Id>
      <BubbleId>3</BubbleId>
      <Status>To Do</Status>
    </Entry>
    <Entry>
      <PointerOffset>263808</PointerOffset>
      <JapaneseText>武器って……
それ、掃除の道具だよ？</JapaneseText>
      <EnglishText/>
      <Notes/>
      <SpeakerId>3</SpeakerId>
      <Id>24</Id>
      <BubbleId>1</BubbleId>
      <Status>To Do</Status>
    </Entry>
    <Entry>
      <PointerOffset>263948</PointerOffset>
      <JapaneseText>でも、チャンバラの時は
すげー役に立ったぜ？</JapaneseText>
      <EnglishText/>
      <Notes/>
      <SpeakerId>4</SpeakerId>
      <Id>25</Id>
      <BubbleId>1</BubbleId>
      <Status>To Do</Status>
    </Entry>
    <Entry>
      <PointerOffset>264256</PointerOffset>
      <JapaneseText>エトちゃん、心配しなくても、
&lt;Dio&gt;くんはまだまだ、
君の助けが必要かもね</JapaneseText>
      <EnglishText/>
      <Notes/>
      <SpeakerId>1</SpeakerId>
      <Id>26</Id>
      <BubbleId>1</BubbleId>
      <Status>To Do</Status>
    </Entry>
    <Entry>
      <PointerOffset>264396</PointerOffset>
      <JapaneseText>な、なんの話だよ、それ！？</JapaneseText>
      <EnglishText/>
      <Notes/>
      <SpeakerId>4</SpeakerId>
      <Id>27</Id>
      <BubbleId>1</BubbleId>
      <Status>To Do</Status>
    </Entry>
  </Strings>
</SceneText>
